social_links_field/__init__.py
social_links_field/apps.py
social_links_field/forms.py
social_links_field/migrations/__init__.py
social_links_field/models.py
social_links_field/screenshot.png
social_links_field/templates/social_links_field/social_links_widget.html
social_links_field/test_app/__init__.py
social_links_field/test_app/admin.py
social_links_field/test_app/apps.py
social_links_field/test_app/migrations/0001_initial.py
social_links_field/test_app/migrations/0002_alter_userprofile_social_links.py
social_links_field/test_app/migrations/__init__.py
social_links_field/test_app/models.py
social_links_field/test_app/tests.py
social_links_field/test_app/views.py
social_links_field/tests.py
social_links_field/views.py
social_links_field/widgets.py
django_social_links_field-0.1.6.dist-info/LICENSE
django_social_links_field-0.1.6.dist-info/METADATA
django_social_links_field-0.1.6.dist-info/WHEEL
django_social_links_field-0.1.6.dist-info/RECORD
