Metadata-Version: 2.1
Name: django-social-links-field
Version: 0.1.6
Summary: A Django form field and widget for managing social media links via models.JSONField
License: MIT
Author: Suraj Singh Bisht
Author-email: surajsinghbisht054@gmail.com
Requires-Python: >=3.10,<4.0
Classifier: License :: OSI Approved :: MIT License
Classifier: Programming Language :: Python :: 3
Classifier: Programming Language :: Python :: 3.10
Classifier: Programming Language :: Python :: 3.11
Classifier: Programming Language :: Python :: 3.12
